notion/__init__.py
notion/block.py
notion/client.py
notion/collection.py
notion/logger.py
notion/maps.py
notion/markdown.py
notion/monitor.py
notion/operations.py
notion/records.py
notion/settings.py
notion/smoke_test.py
notion/space.py
notion/store.py
notion/user.py
notion/utils.py
sinatra_notion-0.0.28.dist-info/LICENSE
sinatra_notion-0.0.28.dist-info/METADATA
sinatra_notion-0.0.28.dist-info/WHEEL
sinatra_notion-0.0.28.dist-info/top_level.txt
sinatra_notion-0.0.28.dist-info/RECORD
