Metadata-Version: 2.1
Name: sinatra-notion
Version: 0.0.28
Summary: Unofficial Python API client for Notion.so
Home-page: https://github.com/jamalex/notion-py
Author: Imran Khan
Author-email: imran@sinatra.ai
License: UNKNOWN
Platform: UNKNOWN
Classifier: Programming Language :: Python :: 3
Classifier: License :: OSI Approved :: MIT License
Classifier: Operating System :: OS Independent
Requires-Python: >=3.5
Requires-Dist: requests
Requires-Dist: commonmark
Requires-Dist: bs4
Requires-Dist: tzlocal
Requires-Dist: python-slugify
Requires-Dist: dictdiffer
Requires-Dist: cached-property
